signalsage/__init__.py
signalsage/processors/__init__.py
signalsage/processors/db_pz_frac.py
signalsage/processors/integrate.py
signalsage/processors/t_pickup.py
signalsage/processors/tail_fit.py
signalsage/processors/tail_fit_2p.py
signalsage/processors/time_point_thresh.py
signalsage-0.1.0.dist-info/licenses/LICENSE
signalsage-0.1.0.dist-info/METADATA
signalsage-0.1.0.dist-info/WHEEL
signalsage-0.1.0.dist-info/top_level.txt
signalsage-0.1.0.dist-info/RECORD
