Metadata-Version: 2.4
Name: signalsage
Version: 0.1.0
Summary: A small dsp processors toolkit for digital signal processing on time-series data
Author-email: Niko Nanda Putra Nila Lay <nikonandap.lay@tum.de>
License: MIT License
Project-URL: Homepage, https://github.com/nikolay327/SignalSage
Project-URL: Source, https://github.com/nikolay327/SignalSage.git
Keywords: signal,time-series,integration,digital signal processing
Classifier: Programming Language :: Python :: 3
Classifier: License :: OSI Approved :: MIT License
Classifier: Operating System :: OS Independent
Requires-Python: >=3.9
License-File: LICENSE
Requires-Dist: numba!=0.53.*,!=0.54.*
Requires-Dist: numpy
Requires-Dist: scipy
Requires-Dist: dspeed
Dynamic: license-file
